.clang-format
.flake8
.gitignore
.gitmodules
CHANGELOG.md
CODEOWNERS
CODE_OF_CONDUCT
Dockerfile
Dockerfile-cuda
Dockerfile-embedded
LICENSE
MANIFEST.in
Makefile
README.md
__init__.py
description.txt
packages.txt
setup.py
./src/opendr/__init__.py
./src/opendr/_setup.py
./src/opendr/_version.py
./src/opendr/control/__init__.py
./src/opendr/engine/__init__.py
./src/opendr/engine/constants.py
./src/opendr/engine/data.py
./src/opendr/engine/datasets.py
./src/opendr/engine/example_learner.py
./src/opendr/engine/learners.py
./src/opendr/engine/target.py
./src/opendr/perception/__init__.py
./src/opendr/perception/semantic_segmentation/__init__.py
./src/opendr/perception/semantic_segmentation/dependencies.ini
./src/opendr/perception/semantic_segmentation/bisenet/CamVid.py
./src/opendr/perception/semantic_segmentation/bisenet/__init__.py
./src/opendr/perception/semantic_segmentation/bisenet/bisenet_learner.py
./src/opendr/perception/semantic_segmentation/bisenet/algorithm/README.md
./src/opendr/perception/semantic_segmentation/bisenet/algorithm/__init__.py
./src/opendr/perception/semantic_segmentation/bisenet/algorithm/utils.py
./src/opendr/perception/semantic_segmentation/bisenet/algorithm/model/__init__.py
./src/opendr/perception/semantic_segmentation/bisenet/algorithm/model/build_BiSeNet.py
./src/opendr/perception/semantic_segmentation/bisenet/algorithm/model/build_contextpath.py
./src/opendr/perception/semantic_segmentation/yolov8_seg/__init__.py
./src/opendr/perception/semantic_segmentation/yolov8_seg/dependencies.ini
./src/opendr/perception/semantic_segmentation/yolov8_seg/yolov8_seg_learner.py
./src/opendr/planning/__init__.py
./src/opendr/simulation/__init__.py
./src/opendr/utils/__init__.py
./src/opendr_toolkit_semantic_segmentation.egg-info/PKG-INFO
./src/opendr_toolkit_semantic_segmentation.egg-info/SOURCES.txt
./src/opendr_toolkit_semantic_segmentation.egg-info/dependency_links.txt
./src/opendr_toolkit_semantic_segmentation.egg-info/requires.txt
./src/opendr_toolkit_semantic_segmentation.egg-info/top_level.txt
src/opendr/_setup.py
src/opendr/_version.py
src/opendr/perception/semantic_segmentation/__init__.py
src/opendr/perception/semantic_segmentation/dependencies.ini
src/opendr/perception/semantic_segmentation/bisenet/CamVid.py
